sage/__init__.py
sage/core.py
sage/main.py
sage/core/__init__.py
sage/core/core.py
sage/plugins/__init__.py
sage/plugins/plugin_template.py
sage/plugins/simple_plugin.py
sage_core-0.2.dist-info/LICENSE
sage_core-0.2.dist-info/METADATA
sage_core-0.2.dist-info/WHEEL
sage_core-0.2.dist-info/top_level.txt
sage_core-0.2.dist-info/RECORD
