Metadata-Version: 2.1
Name: sage-core
Version: 0.2
Summary: Ядро системы плагинов для разработки расширяемых приложений.
Home-page: https://github.com/yourusername/sage-core
Author: AGStudios
Author-email: amckinatorgames@gmail.com
Classifier: Programming Language :: Python :: 3
Classifier: License :: OSI Approved :: MIT License
Classifier: Operating System :: OS Independent
Requires-Python: >=3.6
License-File: LICENSE
